AUTHORS
CHANGES.txt
COPYING
MANIFEST.in
README.txt
readme2.txt
setup.py
hghooks/__init__.py
hghooks/code.py
hghooks/trachooks.py
hghooks.egg-info/PKG-INFO
hghooks.egg-info/SOURCES.txt
hghooks.egg-info/dependency_links.txt
hghooks.egg-info/entry_points.txt
hghooks.egg-info/not-zip-safe
hghooks.egg-info/requires.txt
hghooks.egg-info/top_level.txt