Metadata-Version: 1.0
Name: hghooks
Version: 0.5.2
Summary: A set of useful hooks for Mercurial
Home-page: http://bitbucket.org/lgs/hghooks/
Author: Lorenzo Gil Sanchez
Author-email: lorenzo.gil.sanchez@gmail.com
License: LGPL 3
Keywords: mercurial pep8 pyflakes
Platform: UNKNOWN
